datasphere/__init__.py
datasphere/auth.py
datasphere/changelog.md
datasphere/channel.py
datasphere/client.py
datasphere/config.py
datasphere/files.py
datasphere/fork.py
datasphere/main.py
datasphere/output.py
datasphere/pyenv.py
datasphere/sdk.py
datasphere/utils.py
datasphere/validation.py
datasphere/version.py
datasphere/api/__init__.py
datasphere/google/api/annotations_pb2.py
datasphere/google/api/annotations_pb2.pyi
datasphere/google/api/annotations_pb2_grpc.py
datasphere/google/api/annotations_pb2_grpc.pyi
datasphere/google/api/http_pb2.py
datasphere/google/api/http_pb2.pyi
datasphere/google/api/http_pb2_grpc.py
datasphere/google/api/http_pb2_grpc.pyi
datasphere/google/api/httpbbody_pb2.py
datasphere/google/api/httpbbody_pb2.pyi
datasphere/google/api/httpbbody_pb2_grpc.py
datasphere/google/api/httpbbody_pb2_grpc.pyi
datasphere/google/rpc/code_pb2.py
datasphere/google/rpc/code_pb2.pyi
datasphere/google/rpc/code_pb2_grpc.py
datasphere/google/rpc/code_pb2_grpc.pyi
datasphere/google/rpc/error_details_pb2.py
datasphere/google/rpc/error_details_pb2.pyi
datasphere/google/rpc/error_details_pb2_grpc.py
datasphere/google/rpc/error_details_pb2_grpc.pyi
datasphere/google/rpc/status_pb2.py
datasphere/google/rpc/status_pb2.pyi
datasphere/google/rpc/status_pb2_grpc.py
datasphere/google/rpc/status_pb2_grpc.pyi
datasphere/google/type/timeofday_pb2.py
datasphere/google/type/timeofday_pb2.pyi
datasphere/google/type/timeofday_pb2_grpc.py
datasphere/google/type/timeofday_pb2_grpc.pyi
datasphere/logs/__init__.py
datasphere/logs/config.py
datasphere/logs/logging.yaml
datasphere/yandex/cloud/validation_pb2.py
datasphere/yandex/cloud/validation_pb2.pyi
datasphere/yandex/cloud/validation_pb2_grpc.py
datasphere/yandex/cloud/validation_pb2_grpc.pyi
datasphere/yandex/cloud/access/access_pb2.py
datasphere/yandex/cloud/access/access_pb2.pyi
datasphere/yandex/cloud/access/access_pb2_grpc.py
datasphere/yandex/cloud/access/access_pb2_grpc.pyi
datasphere/yandex/cloud/api/operation_pb2.py
datasphere-0.9.0.dist-info/METADATA
datasphere-0.9.0.dist-info/WHEEL
datasphere-0.9.0.dist-info/entry_points.txt
datasphere-0.9.0.dist-info/top_level.txt
datasphere-0.9.0.dist-info/RECORD
