Metadata-Version: 2.1
Name: datasphere
Version: 0.9.0
Summary: Yandex Cloud DataSphere
Author: Yandex LLC
Author-email: cloud@support.yandex.ru
License: Apache-2.0
Classifier: Programming Language :: Python
Classifier: Programming Language :: Python :: 3.8
Classifier: Programming Language :: Python :: 3.9
Classifier: Programming Language :: Python :: 3.10
Classifier: Programming Language :: Python :: 3.11
Classifier: License :: OSI Approved :: Apache Software License
Requires-Python: >=3.8
Requires-Dist: protobuf
Requires-Dist: googleapis-common-protos
Requires-Dist: grpcio
Requires-Dist: requests
Requires-Dist: pytz
Requires-Dist: pyyaml
Requires-Dist: tabulate>=0.9.0
Requires-Dist: envzy>=0.2.4
